hmc_mir/__init__.py
hmc_mir/align/__init__.py
hmc_mir/align/dtw.py
hmc_mir/align/flex_dtw.py
hmc_mir/align/hstw.py
hmc_mir/align/nwtw.py
hmc_mir/bootleg_score/__init__.py
hmc_mir/bootleg_score/bootleg_score.py
hmc_mir/tsm_tools/__init__.py
hmc_mir/tsm_tools/tsm_tools.py
hmc_mir-0.1.5.dist-info/LICENSE
hmc_mir-0.1.5.dist-info/METADATA
hmc_mir-0.1.5.dist-info/WHEEL
hmc_mir-0.1.5.dist-info/top_level.txt
hmc_mir-0.1.5.dist-info/RECORD
