Metadata-Version: 2.1
Name: hmc-mir
Version: 0.1.5
Summary: Collection of tools developed by HMCs MIR Lab
Home-page: https://github.com/HMC-MIR/hmc-mir-tools
Project-URL: Bug Tracker, https://github.com/HMC-MIR/hmc-mir-tools/issues
Project-URL: Changelog, https://github.com/HMC-MIR/hmc-mir-tools/releases
Classifier: Programming Language :: Python :: 3
Classifier: License :: OSI Approved :: MIT License
Classifier: Intended Audience :: Developers
Requires-Python: >=3.6
License-File: LICENSE
Requires-Dist: numpy (>=1.19)
Requires-Dist: librosa (>=0.10.0)
Requires-Dist: scipy (>=1.5)
Requires-Dist: matplotlib (>=3.5.3)
Requires-Dist: scikit-learn (>=0.24.2)
Requires-Dist: scikit-image (>=0.15.0)
Requires-Dist: opencv-python (>=3.4)
Requires-Dist: pillow (>=8.1.0)
Requires-Dist: numba (>=0.56)
